{
  "configVersion": 1,
  "timestamp": 1618316231297,
  "index": "/index.html",
  "assetGroups": [
    {
      "name": "app",
      "installMode": "prefetch",
      "updateMode": "prefetch",
      "cacheQueryOptions": {
        "ignoreVary": true
      },
      "urls": [
        "/0.dc2d97d84c176409627b.js",
        "/11.25da28021279470986f9.js",
        "/12.04df27234813a3dbb250.js",
        "/13.83e6533c54ea39c757d2.js",
        "/14.09b26da2f04e24628a94.js",
        "/15.4d1a41e28650a23fa632.js",
        "/16.da9d5c3a995bc9383911.js",
        "/17.95181a4303fd19086291.js",
        "/18.9dec64d51b495ea95a24.js",
        "/19.1d0c353c356e5f0a158e.js",
        "/2.577857af37bba0c8be11.js",
        "/20.5093996ff3d7e4b0df73.js",
        "/21.e4f2417c00de526cb4de.js",
        "/22.b67615c75a38b17e6e5f.js",
        "/23.62d1e00431a003ebab78.js",
        "/24.34e09ae5f61985ada0da.js",
        "/25.d1880fdf15bff1cf024b.js",
        "/26.420bae0215c28054273d.js",
        "/3.320a9b3bd82a501cfd8b.js",
        "/4.0e7a28650d2b1fdd38c1.js",
        "/5.52eb0a5d79cc2f988c5e.js",
        "/6.e02b852406901749ecb9.js",
        "/common.86bb18915085c53df02b.js",
        "/favicon.ico",
        "/index.html",
        "/main.5592904bcc1430a72fa6.js",
        "/manifest.webmanifest",
        "/polyfills.5e2ad774c637e78c2ca7.js",
        "/runtime.079931520c8e9210e45d.js",
        "/styles.df8aa0e5aae12decd588.css"
      ],
      "patterns": []
    },
    {
      "name": "assets",
      "installMode": "lazy",
      "updateMode": "prefetch",
      "cacheQueryOptions": {
        "ignoreVary": true
      },
      "urls": [
        "/assets/icons/icon-128x128.png",
        "/assets/icons/icon-144x144.png",
        "/assets/icons/icon-152x152.png",
        "/assets/icons/icon-192x192.png",
        "/assets/icons/icon-384x384.png",
        "/assets/icons/icon-512x512.png",
        "/assets/icons/icon-72x72.png",
        "/assets/icons/icon-96x96.png"
      ],
      "patterns": []
    }
  ],
  "dataGroups": [],
  "hashTable": {
    "/0.dc2d97d84c176409627b.js": "5eb962ddb4bbc5e5d35829e56097ccb10d88abe8",
    "/11.25da28021279470986f9.js": "990fcb6c56bae00d9404e7184c985109cae28964",
    "/12.04df27234813a3dbb250.js": "2d301c8a16093d4e63e56b89e04af4bd91fb407b",
    "/13.83e6533c54ea39c757d2.js": "8fa6ae4bc45bbf143c562bc2c43050ccb931089d",
    "/14.09b26da2f04e24628a94.js": "bcbecd70a799be5bea4b62740d37f82d5c10592a",
    "/15.4d1a41e28650a23fa632.js": "827e505c05febcc521841062ca24c01227fe8438",
    "/16.da9d5c3a995bc9383911.js": "2b0dc212c74d3f7c1fc2164bce43e9f50e7846c4",
    "/17.95181a4303fd19086291.js": "861b62e183216e931dffd68db72638e850051e72",
    "/18.9dec64d51b495ea95a24.js": "6f6e271d8e994f5548ecccf0b779d2c414aa95f1",
    "/19.1d0c353c356e5f0a158e.js": "d78b5baaa1b65b5add0402f62d2f6aeb42fec25b",
    "/2.577857af37bba0c8be11.js": "ed5194ec3061fef5ed60fb727aa8bc8cfff264cf",
    "/20.5093996ff3d7e4b0df73.js": "fdb7cbb675339852e42e50fac52c3737ef5cf64b",
    "/21.e4f2417c00de526cb4de.js": "324f9ad7048045e121059bdc75402efb46765066",
    "/22.b67615c75a38b17e6e5f.js": "1940d32f61a8fa0e4c5aca3dfcdb1f3e4ec53416",
    "/23.62d1e00431a003ebab78.js": "18dcd89bab0439409fe909f867a1d8c518d2e208",
    "/24.34e09ae5f61985ada0da.js": "f490f6addecd0ba949debe1157843a3baf61f0c5",
    "/25.d1880fdf15bff1cf024b.js": "b7fdaa4901147e9d42ad298b0a25a20fe0455c5b",
    "/26.420bae0215c28054273d.js": "56efacb73b87c9fef6463fe1fa68ea6d31b69045",
    "/3.320a9b3bd82a501cfd8b.js": "085512e23fd355713291459c24440f2a7ccc5046",
    "/4.0e7a28650d2b1fdd38c1.js": "e23a556eb508968c51cf1b70af07816d2c98542c",
    "/5.52eb0a5d79cc2f988c5e.js": "a7947d7a64197297cd8553eabfeb2bd1b420740d",
    "/6.e02b852406901749ecb9.js": "6c29696145eeb04f8bb1b28910cdd1615817120c",
    "/assets/icons/icon-128x128.png": "1c5bf0f994b474ea448d70dd14ef2557e8fdf93d",
    "/assets/icons/icon-144x144.png": "8c0ed8dfa72676908882f41354075f0a21fd02a4",
    "/assets/icons/icon-152x152.png": "c02f82ef61846bd1780260a4ab1dd2cd62e6effd",
    "/assets/icons/icon-192x192.png": "2023e1c9f1fe245cb6444109ec32f0f7697ebed4",
    "/assets/icons/icon-384x384.png": "e39193ee39e405020f2df593a2be4b850ce59ec0",
    "/assets/icons/icon-512x512.png": "110257b45576032986eaccec73de2c5c0399ba1c",
    "/assets/icons/icon-72x72.png": "354dd0286b123fd9ff528be05f20b8da608bad53",
    "/assets/icons/icon-96x96.png": "3add8a569b52e9f5009868f89c0900e0b9cc1a69",
    "/common.86bb18915085c53df02b.js": "2c305adf3e5d37ee1f0f2516a502376b10e8cef2",
    "/favicon.ico": "86beab89d4ec4dc243e387c649846ecd3b7dc232",
    "/index.html": "6ba23701aa0bf5ae4d6744a5ee0c97ecc450e2e1",
    "/main.5592904bcc1430a72fa6.js": "62e35757bfd6f798d423fcaa2c2f6c30e8e19c39",
    "/manifest.webmanifest": "3dc95f61214afb2f457f3d007e367b60b02f1943",
    "/polyfills.5e2ad774c637e78c2ca7.js": "d6522f2be785969dddcafa0f2ec556b077b08f84",
    "/runtime.079931520c8e9210e45d.js": "67993e7182d0f7dc49345b564985e57b293da64b",
    "/styles.df8aa0e5aae12decd588.css": "56a8389c5828a99013706064fd035382515e027e"
  },
  "navigationUrls": [
    {
      "positive": true,
      "regex": "^\\/.*$"
    },
    {
      "positive": false,
      "regex": "^\\/(?:.+\\/)?[^/]*\\.[^/]*$"
    },
    {
      "positive": false,
      "regex": "^\\/(?:.+\\/)?[^/]*__[^/]*$"
    },
    {
      "positive": false,
      "regex": "^\\/(?:.+\\/)?[^/]*__[^/]*\\/.*$"
    }
  ]
}